{
 "SoundBanksInfo": {
  "Platform": "Windows",
  "BasePlatform": "Windows",
  "SchemaVersion": "16",
  "SoundBankVersion": "150",
  "SoundBanks": [
   {
    "Id": "4075332698",
    "Type": "Bus",
    "GUID": "{3F793FCE-D4BE-44E6-BB7C-AD68F0A49ECA}",
    "Language": "SFX",
    "Hash": "{03B5EEA3-9BEF-E437-2044-B0959DE0CBF4}",
    "ObjectPath": "beach",
    "ShortName": "beach",
    "Path": "Bus/beach.bnk",
    "Plugins": {
     "ShareSets": [
      {
       "Id": "48620415",
       "Name": "Have_U_Ever_Been_Outside",
       "ObjectPath": "\\Effects\\Factory Effects\\RoomVerb\\Exteriors\\Have_U_Ever_Been_Outside",
       "GUID": "{FE29AE8D-FD86-4652-A95D-68D32F5760EC}",
       "LibName": "Wwise RoomVerb",
       "LibId": "7733251"
      }
     ]
    },
    "AuxBusses": [
     {
      "Id": "4075332698",
      "Name": "beach",
      "ObjectPath": "\\Master-Mixer Hierarchy\\Default Work Unit\\Master Audio Bus\\beach",
      "GUID": "{3F793FCE-D4BE-44E6-BB7C-AD68F0A49ECA}",
      "PluginRefs": {
       "ShareSets": [
        {
         "Id": "48620415"
        }
       ]
      }
     }
    ]
   }
  ],
  "FileHash": "{12539E15-9BA4-E8AD-9E12-4C4FDF3043AD}"
 }
}